spectrautils/__init__.py
spectrautils/common_utils.py
spectrautils/logging_utils.py
spectrautils/print_utils.py
spectrautils/time_utils.py
spectrautils/onnx_utils/__init__.py
spectrautils/onnx_utils/common_tools.py
spectrautils/onnx_utils/compare_two_onnx_weight.py
spectrautils/onnx_utils/config_spectrautils.py
spectrautils/onnx_utils/io_utils.py
spectrautils/onnx_utils/operator_utils.py
spectrautils/onnx_utils/remove_initializer_from_input.py
spectrautils/onnx_utils/visualize.py
spectrautils-0.3.5.dist-info/METADATA
spectrautils-0.3.5.dist-info/WHEEL
spectrautils-0.3.5.dist-info/top_level.txt
spectrautils-0.3.5.dist-info/RECORD
