Metadata-Version: 2.1
Name: spectrautils
Version: 0.3.5
Summary: A powerful tools for python
Author: bruce_cui
Author-email: summer56567@163.com
Requires-Dist: termcolor >=2.3.0
Requires-Dist: colorama >=0.4.4
Requires-Dist: onnxruntime-gpu >=1.18.0
Requires-Dist: onnx >=1.16.1
Requires-Dist: tqdm >=4.67.1
Requires-Dist: pandas >=1.5.3
Requires-Dist: holoviews >=1.17.1
Requires-Dist: hvplot >=0.10.0
